dw3d/__init__.py
dw3d/edt.py
dw3d/io.py
dw3d/mask_reconstruction.py
dw3d/mesh_surgery.py
dw3d/mesh_utilities.py
dw3d/points_on_edt.py
dw3d/reconstruction_algorithm.py
dw3d/reconstruction_algorithm_factory.py
dw3d/score_computation.py
dw3d/segmentation.py
dw3d/tesselation.py
dw3d/tesselation_graph.py
dw3d/viewing.py
dw3d/watershed.py
delaunay_watershed_3d-0.3.6.dist-info/METADATA
delaunay_watershed_3d-0.3.6.dist-info/WHEEL
delaunay_watershed_3d-0.3.6.dist-info/top_level.txt
delaunay_watershed_3d-0.3.6.dist-info/RECORD
