Metadata-Version: 2.1
Name: delaunay_watershed_3d
Version: 0.3.6
Summary: Geometrical reconstruction of cell assemblies from instance segmentations
Home-page: https://github.com/VirtualEmbryo/delaunay-watershed
Author: Sacha Ichbiah
Author-email: sacha.ichbiah@college-de-france.fr
Maintainer: Matthieu Perez
Maintainer-email: matthieu.perez@college-de-france.fr
License: CC BY-NC-SA 4.0
Project-URL: Team website, https://www.turlierlab.com/
Classifier: Programming Language :: Python :: 3
Classifier: Operating System :: POSIX :: Linux
Classifier: Operating System :: MacOS
Classifier: Intended Audience :: Science/Research
Requires-Python: >=3.10
Requires-Dist: edt >=2.4.0
Requires-Dist: meshio >=5.3.4
Requires-Dist: networkx >=2.8.0
Requires-Dist: numpy >=1.24.0
Requires-Dist: scikit-image >=0.20.0
Requires-Dist: scipy >=1.9.3
Requires-Dist: trimesh >=4.0.0
Provides-Extra: viewing
Requires-Dist: napari[all] ; extra == 'viewing'
Requires-Dist: polyscope >=1.2.0 ; extra == 'viewing'
Requires-Dist: matplotlib >=3.3.1 ; extra == 'viewing'
